transcriptformer/__init__.py
transcriptformer/datasets.py
transcriptformer/cli/__init__.py
transcriptformer/cli/download_artifacts.py
transcriptformer/cli/download_data.py
transcriptformer/cli/inference.py
transcriptformer/cli/conf/inference_config.yaml
transcriptformer/data/__init__.py
transcriptformer/data/bulk_download.py
transcriptformer/data/dataclasses.py
transcriptformer/data/dataloader.py
transcriptformer/model/__init__.py
transcriptformer/model/embedding_surgery.py
transcriptformer/model/inference.py
transcriptformer/model/layers.py
transcriptformer/model/losses.py
transcriptformer/model/masks.py
transcriptformer/model/model.py
transcriptformer/tokenizer/__init__.py
transcriptformer/tokenizer/tokenizer.py
transcriptformer/tokenizer/vocab.py
transcriptformer/utils/__init__.py
transcriptformer/utils/utils.py
transcriptformer-0.6.1.dist-info/METADATA
transcriptformer-0.6.1.dist-info/WHEEL
transcriptformer-0.6.1.dist-info/entry_points.txt
transcriptformer-0.6.1.dist-info/licenses/LICENSE.md
transcriptformer-0.6.1.dist-info/RECORD
