Metadata-Version: 2.4
Name: transcriptformer
Version: 0.6.1
Summary: A transformer model for gene expression data
Project-URL: Bug Tracker, https://github.com/czi-ai/transcriptformer/issues
Project-URL: Homepage, https://github.com/czi-ai/transcriptformer
License: MIT
License-File: LICENSE.md
Classifier: Programming Language :: Python :: 3 :: Only
Classifier: Programming Language :: Python :: 3.11
Classifier: Programming Language :: Python :: 3.12
Requires-Python: >=3.11
Requires-Dist: anndata==0.11.4
Requires-Dist: boto3==1.38.27
Requires-Dist: cellxgene-census==1.17
Requires-Dist: h5py==3.14
Requires-Dist: hydra-core==1.3.2
Requires-Dist: numpy==2.2.6
Requires-Dist: pandas==2.2.2
Requires-Dist: psutil==5.9
Requires-Dist: pynvml==12
Requires-Dist: pytest==8.4
Requires-Dist: pytorch-lightning==2.5.1
Requires-Dist: requests==2.32.3
Requires-Dist: scanpy==1.11.2
Requires-Dist: scipy==1.15.3
Requires-Dist: timeout-decorator==0.5
Requires-Dist: torch==2.5.1
Provides-Extra: build
Requires-Dist: hatch>=1.14.1; extra == 'build'
Requires-Dist: twine>=6.1; extra == 'build'
Requires-Dist: wheel>=0.45.1; extra == 'build'
Provides-Extra: dev
Requires-Dist: pre-commit; extra == 'dev'
Requires-Dist: pytest==8.4; extra == 'dev'
